github_issue_parser_mcp/__init__.py
github_issue_parser_mcp/__main__.py
github_issue_parser_mcp/parser.py
github_issue_parser_mcp-2.0.0.dist-info/licenses/LICENSE
github_issue_parser_mcp-2.0.0.dist-info/METADATA
github_issue_parser_mcp-2.0.0.dist-info/WHEEL
github_issue_parser_mcp-2.0.0.dist-info/entry_points.txt
github_issue_parser_mcp-2.0.0.dist-info/top_level.txt
github_issue_parser_mcp-2.0.0.dist-info/RECORD
