Metadata-Version: 2.4
Name: github-issue-parser-mcp
Version: 2.0.0
Summary: An MCP server that parses GitHub issues and returns formatted plain text content
Author-email: Anionex <your.email@example.com>
Project-URL: Homepage, https://github.com/Anionex/github-issue-parser-MCP-server
Project-URL: Bug Tracker, https://github.com/Anionex/github-issue-parser-MCP-server/issues
Classifier: Programming Language :: Python :: 3
Classifier: License :: OSI Approved :: MIT License
Classifier: Operating System :: OS Independent
Requires-Python: >=3.8
License-File: LICENSE
Requires-Dist: fastmcp>=0.1.0
Requires-Dist: requests>=2.28.0
Requires-Dist: beautifulsoup4>=4.11.0
Dynamic: license-file
